CHANGES.txt
MANIFEST.in
README.rst
pytest.ini
requirements.txt
setup.py
PyramidAuthService.egg-info/PKG-INFO
PyramidAuthService.egg-info/SOURCES.txt
PyramidAuthService.egg-info/dependency_links.txt
PyramidAuthService.egg-info/not-zip-safe
PyramidAuthService.egg-info/requires.txt
PyramidAuthService.egg-info/top_level.txt
authservice/__init__.py
authservice/jwt_security.py
authservice/security.py
authservice/web_security.py
authservice/models/RootFactory.py
authservice/models/__init__.py
authservice/models/group.py
authservice/models/meta.py
authservice/models/user.py
authservice/scripts/__init__.py
authservice/scripts/initializedb.py
authservice/templates/login.jinja2
authservice/views/__init__.py
authservice/views/jwt_auth.py
authservice/views/web_auth.py