Metadata-Version: 1.1
Name: PyramidAuthService
Version: 0.1
Summary: Pyramid AuthService
Home-page: UNKNOWN
Author: Steven Locke
Author-email: steve.m.locke@gmail.com
License: UNKNOWN
Keywords: pyramid jwt auth
Platform: UNKNOWN
Classifier: Programming Language :: Python
Classifier: Framework :: Pyramid
Classifier: Topic :: Internet :: WWW/HTTP
Classifier: Topic :: Internet :: WWW/HTTP :: WSGI :: Application
